mecher_base_api_client/__init__.py
mecher_base_api_client/api_client.py
mecher_base_api_client/utils.py
mecher_base_api_client-0.0.21.dist-info/METADATA
mecher_base_api_client-0.0.21.dist-info/WHEEL
mecher_base_api_client-0.0.21.dist-info/top_level.txt
mecher_base_api_client-0.0.21.dist-info/RECORD
