Metadata-Version: 2.1
Name: mecher_base_api_client
Version: 0.0.21
Summary: Base for API clients
Home-page: https://github.com/MaximChernyak98/mecher_base_api_client
Maintainer: mecher
Keywords: testing
Requires-Dist: allure-pytest==2.13.5
Requires-Dist: requests==2.32.3
